publish.py
livekit_plugins_chinese-0.1.0.dist-info/licenses/LICENSE
livekit_plugins_chinese-0.1.0.dist-info/METADATA
livekit_plugins_chinese-0.1.0.dist-info/WHEEL
livekit_plugins_chinese-0.1.0.dist-info/top_level.txt
livekit_plugins_chinese-0.1.0.dist-info/RECORD
