Metadata-Version: 2.4
Name: livekit-plugins-chinese
Version: 0.1.0
Requires-Python: >=3.9
License-File: LICENSE
Requires-Dist: livekit-agents==1.1.2
Dynamic: license-file
